docs/.nojekyll
docs/Makefile
docs/api.rst
docs/conf.py
docs/index.rst
docs/requirements.txt
docs/_static/css/custom.css
docs/_templates/custom-module-template.rst
docs/_templates/autoapi/index.rst
docs/_templates/autoapi/macros.rst
docs/_templates/autoapi/python/attribute.rst
docs/_templates/autoapi/python/class.rst
docs/_templates/autoapi/python/data.rst
docs/_templates/autoapi/python/exception.rst
docs/_templates/autoapi/python/function.rst
docs/_templates/autoapi/python/method.rst
docs/_templates/autoapi/python/module.rst
docs/_templates/autoapi/python/package.rst
docs/_templates/autoapi/python/property.rst
ptovnetlab/_version.py
ptovnetlab/arista_poller.py
ptovnetlab/arista_sanitizer.py
ptovnetlab/data_classes.py
ptovnetlab/gns3_worker.py
ptovnetlab/ptovnetlab.py
ptovnetlab/ptovnetlab_cli.py
ptovnetlab/workflow_semaphore
tests/contexts.py
tests/test_vdcnod.py
tests/trashbin/arista_poller-2.py
ptovnetlab-0.0.5.3.dist-info/LICENSE
ptovnetlab-0.0.5.3.dist-info/METADATA
ptovnetlab-0.0.5.3.dist-info/WHEEL
ptovnetlab-0.0.5.3.dist-info/top_level.txt
ptovnetlab-0.0.5.3.dist-info/RECORD
