Metadata-Version: 2.2
Name: ptovnetlab
Version: 0.0.5.3
Summary: Gets run-state details from a list of Arista switches and builds a GNS3 virtual-lab to emulate them.
Author-email: Mencken Davidson <mencken@gmail.com>
Maintainer-email: Mencken Davidson <mencken@gmail.com>
License: Modified BSD License
Project-URL: Homepage, https://menckend.github.io/dcnodatg
Project-URL: Repository, https://github.com/menckend/dcnodatg.git
Project-URL: Issues, https://github.com/menckend/dcnodatg/issues
Keywords: arista,eapi,eos,gns3,lab,virtual,ceos
Requires-Python: >=3.11
License-File: LICENSE
Requires-Dist: pyeapi
Requires-Dist: docker
Requires-Dist: build
Requires-Dist: asyncio
Requires-Dist: requests
Requires-Dist: aiohttp
Requires-Dist: aiodocker
